CHANGELOG.md
LICENSE.txt
MANIFEST.in
README.md
requirements.txt
setup.cfg
setup.py
agaveflask/__init__.py
agaveflask/auth.py
agaveflask/config.py
agaveflask/errors.py
agaveflask/models.py
agaveflask/store.py
agaveflask/utils.py
agaveflask.egg-info/PKG-INFO
agaveflask.egg-info/SOURCES.txt
agaveflask.egg-info/dependency_links.txt
agaveflask.egg-info/not-zip-safe
agaveflask.egg-info/requires.txt
agaveflask.egg-info/top_level.txt