Metadata-Version: 1.1
Name: agaveflask
Version: 0.2.0
Summary: Common package for authoring Agave services in flask/Flask-RESTful
Home-page: https://bitbucket.org/agaveapi/agaveflask
Author: Joe Stubbs
Author-email: jstubbs@tacc.utexas.edu
License: BSD
Platform: UNKNOWN
Classifier: Development Status :: 2 - Pre-Alpha
Classifier: Intended Audience :: Developers
Classifier: License :: OSI Approved :: BSD License
Classifier: Natural Language :: English
Classifier: Programming Language :: Python :: 3.4
Classifier: Programming Language :: Python :: 3.5
